renag/__init__.py
renag/__main__.py
renag/complainer.py
renag/complaint.py
renag/custom_types.py
renag/tests/test_utils.py
renag/utils.py
renag-0.4.4.dist-info/entry_points.txt
renag-0.4.4.dist-info/LICENSE
renag-0.4.4.dist-info/WHEEL
renag-0.4.4.dist-info/METADATA
renag-0.4.4.dist-info/RECORD
